dzr_import/__init__.py
dzr_import/dec.py
dzr_import/main.py
dzr_import/tag.py
dzr_import/tracks.py
dzr_import-0.1.2.dist-info/METADATA
dzr_import-0.1.2.dist-info/WHEEL
dzr_import-0.1.2.dist-info/entry_points.txt
dzr_import-0.1.2.dist-info/RECORD
